HyperEvalSR/__init__.py
HyperEvalSR/algorithms.py
HyperEvalSR/data.py
HyperEvalSR/metrics.py
HyperEvalSR-1.0.1.dist-info/LICENSE
HyperEvalSR-1.0.1.dist-info/METADATA
HyperEvalSR-1.0.1.dist-info/WHEEL
HyperEvalSR-1.0.1.dist-info/top_level.txt
HyperEvalSR-1.0.1.dist-info/RECORD
