Metadata-Version: 2.1
Name: HyperEvalSR
Version: 1.0.1
Summary: An open source python package for super-resolution/recovery quality evaluation of hyperspectral images, including RMSE, ERGAS, SSIM, RSNR, PSNR, CC, DD, and SAM.
Home-page: https://github.com/jingmengzhiyue/HyperEvalSR
Author: jingmengzhiyue
Author-email: jingmengzhiyue@gmail.com
Classifier: Programming Language :: Python :: 3
Classifier: License :: OSI Approved :: MIT License
Classifier: Operating System :: OS Independent
Requires-Python: >=3.6
License-File: LICENSE
Requires-Dist: matplotlib
Requires-Dist: numpy
Requires-Dist: scipy
Requires-Dist: tifffile
